cachetclient/__init__.py
cachetclient/base.py
cachetclient/cli.py
cachetclient/client.py
cachetclient/httpclient.py
cachetclient/utils.py
cachetclient/v1/__init__.py
cachetclient/v1/client.py
cachetclient/v1/component_groups.py
cachetclient/v1/components.py
cachetclient/v1/enums.py
cachetclient/v1/incident_updates.py
cachetclient/v1/incidents.py
cachetclient/v1/metric_points.py
cachetclient/v1/metrics.py
cachetclient/v1/ping.py
cachetclient/v1/schedules.py
cachetclient/v1/subscribers.py
cachetclient/v1/version.py
cachet_client-4.0.1.dist-info/LICENSE
cachet_client-4.0.1.dist-info/METADATA
cachet_client-4.0.1.dist-info/WHEEL
cachet_client-4.0.1.dist-info/entry_points.txt
cachet_client-4.0.1.dist-info/top_level.txt
cachet_client-4.0.1.dist-info/RECORD
