Metadata-Version: 2.1
Name: cachet-client
Version: 4.0.1
Summary: A python 3 client for the Cachet API
Home-page: https://github.com/zettaio/cachet-client
Author: Einar Forselv
Author-email: eforselv@gmail.com
Maintainer: Einar Forselv
Maintainer-email: eforselv@gmail.com
License: UNKNOWN
Keywords: cachet,client,api
Platform: UNKNOWN
Classifier: Programming Language :: Python
Classifier: Programming Language :: Python :: 3
Classifier: Programming Language :: Python :: 3.6
Classifier: Programming Language :: Python :: 3.7
Classifier: Programming Language :: Python :: 3.8
Classifier: Programming Language :: Python :: 3.9
Classifier: License :: OSI Approved :: BSD License
Requires-Python: >=3.5
Requires-Dist: requests (>=2.21.0)
